[{"G/T": 12, "coordinates": [60,-50], "servers": ["AAL", "SVL", "TRL"], "marker": "r", "name": "Ship1", "operative": true}, {"G/T": 12, "coordinates": [61,-49.2026714789407], "servers": ["AAL", "SVL", "TRL"], "marker": "r", "name": "Ship2", "operative": true}, {"G/T": 12, "coordinates": [59,-47], "servers": ["AAL", "SVL", "TRL"], "marker": "r", "name": "Ship3", "operative": true}, {"G/T": 12, "coordinates": [60,-42.20745354693872], "servers": ["AAL", "SVL", "TRL"], "marker": "r", "name": "Ship4", "operative": true}, {"G/T": 12, "coordinates": [55,-45.5], "servers": ["AAL", "SVL", "TRL"], "marker": "r", "name": "Ship5", "operative": true}, {"G/T": 12, "coordinates": [56,-43], "servers": ["AAL", "SVL", "TRL"], "marker": "r", "name": "Ship6", "operative": true}]
